caixa_de_ferramentas/__init__.py
caixa_de_ferramentas/azure_blob_api.py
caixa_de_ferramentas/azure_key_vault_api.py
caixa_de_ferramentas/azure_tables_api.py
caixa_de_ferramentas/etherscan_api.py
caixa_de_ferramentas/kafka_client_api.py
caixa_de_ferramentas/redis_client_api.py
caixa_de_ferramentas/testing_package.py
caixa_de_ferramentas-0.1.3.dist-info/METADATA
caixa_de_ferramentas-0.1.3.dist-info/WHEEL
caixa_de_ferramentas-0.1.3.dist-info/RECORD
