Metadata-Version: 2.1
Name: caixa-de-ferramentas
Version: 0.1.3
Summary: 
Author: Marco Menezes
Author-email: marcoaurelioreislima@gmail.com
Requires-Python: >=3.7,<4.0
Classifier: Programming Language :: Python :: 3
Classifier: Programming Language :: Python :: 3.7
Classifier: Programming Language :: Python :: 3.8
Classifier: Programming Language :: Python :: 3.9
Classifier: Programming Language :: Python :: 3.10
Classifier: Programming Language :: Python :: 3.11
Requires-Dist: azure-data-tables (>=12.4.3,<13.0.0)
Requires-Dist: azure-keyvault-secrets (>=4.7.0,<5.0.0)
Requires-Dist: azure-storage-blob (>=12.17.0,<13.0.0)
Requires-Dist: kafka-python (>=2.0.2,<3.0.0)
Requires-Dist: redis (>=5.0.0,<6.0.0)
